MANIFEST.in
README.rst
setup.py
cms_named_menus/__init__.py
cms_named_menus/admin.py
cms_named_menus/models.py
cms_named_menus/migrations/0001_initial.py
cms_named_menus/migrations/0002_auto_20150227_1436.py
cms_named_menus/migrations/__init__.py
cms_named_menus/south_migrations/0001_initial.py
cms_named_menus/south_migrations/__init__.py
cms_named_menus/static/cmsnamedmenus/css/admin.css
cms_named_menus/static/cmsnamedmenus/css/nestable.css
cms_named_menus/static/cmsnamedmenus/js/admin.js
cms_named_menus/static/cmsnamedmenus/js/admin.js.map
cms_named_menus/templates/cms_named_menus/admin_select.html
cms_named_menus/templates/cms_named_menus/change_form.html
cms_named_menus/templates/cms_named_menus/fieldset.html
cms_named_menus/templatetags/__init__.py
cms_named_menus/templatetags/named_cms_menu_tags.py
django_cms_named_menus.egg-info/PKG-INFO
django_cms_named_menus.egg-info/SOURCES.txt
django_cms_named_menus.egg-info/dependency_links.txt
django_cms_named_menus.egg-info/not-zip-safe
django_cms_named_menus.egg-info/requires.txt
django_cms_named_menus.egg-info/top_level.txt