Metadata-Version: 1.0
Name: django-cms-named-menus
Version: 0.1.10
Summary: Allows you to add named menus like Wordpress
Home-page: https://github.com/ryanbagwell/django-cms-named-menus/
Author: Ryan Bagwell
Author-email: ryan@ryanbagwell.com
License: BSD
Platform: UNKNOWN
